<?xml version="1.0" encoding="UTF-8"?>
<MetaDataObject xmlns="http://v8.1c.ru/8.3/MDClasses" xmlns:app="http://v8.1c.ru/8.2/managed-application/core" xmlns:cfg="http://v8.1c.ru/8.1/data/enterprise/current-config" xmlns:cmi="http://v8.1c.ru/8.2/managed-application/cmi" xmlns:ent="http://v8.1c.ru/8.1/data/enterprise" xmlns:lf="http://v8.1c.ru/8.2/managed-application/logform" xmlns:style="http://v8.1c.ru/8.1/data/ui/style" xmlns:sys="http://v8.1c.ru/8.1/data/ui/fonts/system" xmlns:v8="http://v8.1c.ru/8.1/data/core" xmlns:v8ui="http://v8.1c.ru/8.1/data/ui" xmlns:web="http://v8.1c.ru/8.1/data/ui/colors/web" xmlns:win="http://v8.1c.ru/8.1/data/ui/colors/windows" xmlns:xen="http://v8.1c.ru/8.3/xcf/enums" xmlns:xpr="http://v8.1c.ru/8.3/xcf/predef" xmlns:xr="http://v8.1c.ru/8.3/xcf/readable" xmlns:xs="http://www.w3.org/2001/XMLSchema" xmlns:xsi="http://www.w3.org/2001/XMLSchema-instance" version="2.20">
	<Constant uuid="f2d50783-9cd9-42f3-b309-03088ebd7148">
		<InternalInfo>
			<xr:GeneratedType name="ConstantManager.МестоХраненияБЭБ" category="Manager">
				<xr:TypeId>0b8ce4c9-de6e-4e23-9cfe-beb894a0f177</xr:TypeId>
				<xr:ValueId>bbb1e61f-d2a1-4c95-827e-ea5fe7d375d6</xr:ValueId>
			</xr:GeneratedType>
			<xr:GeneratedType name="ConstantValueManager.МестоХраненияБЭБ" category="ValueManager">
				<xr:TypeId>ad8a3187-f7b3-42b4-8035-87dbde53de05</xr:TypeId>
				<xr:ValueId>151b678c-dc8e-477e-a7f7-2ff67453d490</xr:ValueId>
			</xr:GeneratedType>
			<xr:GeneratedType name="ConstantValueKey.МестоХраненияБЭБ" category="ValueKey">
				<xr:TypeId>3ff5a016-7142-4b9f-8e8d-2f2043e317cf</xr:TypeId>
				<xr:ValueId>e0990eec-2c57-41a5-a600-fec9cbb9e1f5</xr:ValueId>
			</xr:GeneratedType>
		</InternalInfo>
		<Properties>
			<Name>МестоХраненияБЭБ</Name>
			<Synonym>
				<v8:item>
					<v8:lang>ru</v8:lang>
					<v8:content>Место хранения БЭБ</v8:content>
				</v8:item>
			</Synonym>
			<Comment/>
			<Type>
				<v8:Type>cfg:CatalogRef.МестаХранения</v8:Type>
			</Type>
			<UseStandardCommands>false</UseStandardCommands>
			<DefaultForm/>
			<ExtendedPresentation/>
			<Explanation/>
			<PasswordMode>false</PasswordMode>
			<Format/>
			<EditFormat/>
			<ToolTip/>
			<MarkNegatives>false</MarkNegatives>
			<Mask/>
			<MultiLine>false</MultiLine>
			<ExtendedEdit>false</ExtendedEdit>
			<MinValue xsi:nil="true"/>
			<MaxValue xsi:nil="true"/>
			<FillChecking>DontCheck</FillChecking>
			<ChoiceFoldersAndItems>Items</ChoiceFoldersAndItems>
			<ChoiceParameterLinks/>
			<ChoiceParameters/>
			<QuickChoice>Auto</QuickChoice>
			<ChoiceForm/>
			<LinkByType/>
			<ChoiceHistoryOnInput>Auto</ChoiceHistoryOnInput>
			<DataLockControlMode>Automatic</DataLockControlMode>
			<DataHistory>DontUse</DataHistory>
			<UpdateDataHistoryImmediatelyAfterWrite>false</UpdateDataHistoryImmediatelyAfterWrite>
			<ExecuteAfterWriteDataHistoryVersionProcessing>false</ExecuteAfterWriteDataHistoryVersionProcessing>
		</Properties>
	</Constant>
</MetaDataObject>