<?xml version="1.0" encoding="UTF-8"?>
<MetaDataObject xmlns="http://v8.1c.ru/8.3/MDClasses" xmlns:app="http://v8.1c.ru/8.2/managed-application/core" xmlns:cfg="http://v8.1c.ru/8.1/data/enterprise/current-config" xmlns:cmi="http://v8.1c.ru/8.2/managed-application/cmi" xmlns:ent="http://v8.1c.ru/8.1/data/enterprise" xmlns:lf="http://v8.1c.ru/8.2/managed-application/logform" xmlns:style="http://v8.1c.ru/8.1/data/ui/style" xmlns:sys="http://v8.1c.ru/8.1/data/ui/fonts/system" xmlns:v8="http://v8.1c.ru/8.1/data/core" xmlns:v8ui="http://v8.1c.ru/8.1/data/ui" xmlns:web="http://v8.1c.ru/8.1/data/ui/colors/web" xmlns:win="http://v8.1c.ru/8.1/data/ui/colors/windows" xmlns:xen="http://v8.1c.ru/8.3/xcf/enums" xmlns:xpr="http://v8.1c.ru/8.3/xcf/predef" xmlns:xr="http://v8.1c.ru/8.3/xcf/readable" xmlns:xs="http://www.w3.org/2001/XMLSchema" xmlns:xsi="http://www.w3.org/2001/XMLSchema-instance" version="2.20">
	<DocumentJournal uuid="d7256b5a-2e11-4f8b-8879-a9f79d2641f2">
		<InternalInfo>
			<xr:GeneratedType name="DocumentJournalSelection.ОперационныйЖурнал" category="Selection">
				<xr:TypeId>695c0ec2-cb3d-4df5-8fc1-51f0cc550271</xr:TypeId>
				<xr:ValueId>24392be5-b2c8-4497-b490-b0ca5efff120</xr:ValueId>
			</xr:GeneratedType>
			<xr:GeneratedType name="DocumentJournalList.ОперационныйЖурнал" category="List">
				<xr:TypeId>03f54982-0ae3-4412-b8ad-1ff31655f322</xr:TypeId>
				<xr:ValueId>94bc4fe3-e7b7-4f38-8e2f-397871dae95a</xr:ValueId>
			</xr:GeneratedType>
			<xr:GeneratedType name="DocumentJournalManager.ОперационныйЖурнал" category="Manager">
				<xr:TypeId>4cf9fb45-f8c2-4928-af5b-35b92f3cae2f</xr:TypeId>
				<xr:ValueId>de5e5897-5ca3-45ba-af95-07986a6b7d07</xr:ValueId>
			</xr:GeneratedType>
		</InternalInfo>
		<Properties>
			<Name>ОперационныйЖурнал</Name>
			<Synonym>
				<v8:item>
					<v8:lang>ru</v8:lang>
					<v8:content>Операционный журнал</v8:content>
				</v8:item>
			</Synonym>
			<Comment/>
			<DefaultForm>DocumentJournal.ОперационныйЖурнал.Form.ФормаСписка</DefaultForm>
			<AuxiliaryForm/>
			<UseStandardCommands>true</UseStandardCommands>
			<RegisteredDocuments>
				<xr:Item xsi:type="xr:MDObjectRef">Document.ОткрытиеСчетаДепо</xr:Item>
				<xr:Item xsi:type="xr:MDObjectRef">Document.ОперацииЦБ</xr:Item>
				<xr:Item xsi:type="xr:MDObjectRef">Document.ОткрытиеРазделаСчетаДепо</xr:Item>
				<xr:Item xsi:type="xr:MDObjectRef">Document.ЗакрытиеСчетаДепо</xr:Item>
				<xr:Item xsi:type="xr:MDObjectRef">Document.НазначениеПредставителяСчетаДепо</xr:Item>
				<xr:Item xsi:type="xr:MDObjectRef">Document.ОтменаПредставителяСчетаДепо</xr:Item>
				<xr:Item xsi:type="xr:MDObjectRef">Document.Выписка</xr:Item>
				<xr:Item xsi:type="xr:MDObjectRef">Document.КорректировкаРеквизитовСчетаДепо</xr:Item>
			</RegisteredDocuments>
			<IncludeHelpInContents>true</IncludeHelpInContents>
			<ListPresentation/>
			<ExtendedListPresentation/>
			<Explanation/>
		</Properties>
		<ChildObjects>
			<Column uuid="1f518a76-b62b-4c70-8d1f-d95a64bc679e">
				<Properties>
					<Name>ВидОперации</Name>
					<Synonym>
						<v8:item>
							<v8:lang>ru</v8:lang>
							<v8:content>Вид операции</v8:content>
						</v8:item>
					</Synonym>
					<Comment/>
					<Indexing>Index</Indexing>
					<References>
						<xr:Item xsi:type="xr:MDObjectRef">Document.ОперацииЦБ.Attribute.ВидОперацииД</xr:Item>
					</References>
				</Properties>
			</Column>
			<Column uuid="2fbe5b68-94d7-4134-8f41-9450a8a8b32c">
				<Properties>
					<Name>Основание</Name>
					<Synonym>
						<v8:item>
							<v8:lang>ru</v8:lang>
							<v8:content>Основание</v8:content>
						</v8:item>
					</Synonym>
					<Comment/>
					<Indexing>DontIndex</Indexing>
					<References>
						<xr:Item xsi:type="xr:MDObjectRef">Document.ОткрытиеСчетаДепо.Attribute.ДокументОснование</xr:Item>
						<xr:Item xsi:type="xr:MDObjectRef">Document.ОперацииЦБ.Attribute.ДокументОснование</xr:Item>
						<xr:Item xsi:type="xr:MDObjectRef">Document.ОткрытиеРазделаСчетаДепо.Attribute.ДокументОснование</xr:Item>
						<xr:Item xsi:type="xr:MDObjectRef">Document.НазначениеПредставителяСчетаДепо.Attribute.ДокументОснование</xr:Item>
						<xr:Item xsi:type="xr:MDObjectRef">Document.ЗакрытиеСчетаДепо.Attribute.ДокументОснование</xr:Item>
						<xr:Item xsi:type="xr:MDObjectRef">Document.ОтменаПредставителяСчетаДепо.Attribute.ДокументОснование</xr:Item>
					</References>
				</Properties>
			</Column>
			<Column uuid="4c60de09-27c3-4c48-83c8-95f660d19228">
				<Properties>
					<Name>Инициатор</Name>
					<Synonym>
						<v8:item>
							<v8:lang>ru</v8:lang>
							<v8:content>Инициатор</v8:content>
						</v8:item>
					</Synonym>
					<Comment/>
					<Indexing>IndexWithAdditionalOrder</Indexing>
					<References>
						<xr:Item xsi:type="xr:MDObjectRef">Document.ОткрытиеСчетаДепо.Attribute.ВладелецСчета</xr:Item>
						<xr:Item xsi:type="xr:MDObjectRef">Document.ОперацииЦБ.Attribute.Инициатор</xr:Item>
						<xr:Item xsi:type="xr:MDObjectRef">Document.ОткрытиеРазделаСчетаДепо.Attribute.ВладелецСчета</xr:Item>
						<xr:Item xsi:type="xr:MDObjectRef">Document.НазначениеПредставителяСчетаДепо.Attribute.ВладелецСчета</xr:Item>
						<xr:Item xsi:type="xr:MDObjectRef">Document.ЗакрытиеСчетаДепо.Attribute.ВладелецСчета</xr:Item>
					</References>
				</Properties>
			</Column>
			<Column uuid="6fe0d323-c831-43f3-9bd5-1510fdf54ee0">
				<Properties>
					<Name>СчетДепо</Name>
					<Synonym>
						<v8:item>
							<v8:lang>ru</v8:lang>
							<v8:content>Счет депо</v8:content>
						</v8:item>
					</Synonym>
					<Comment/>
					<Indexing>Index</Indexing>
					<References>
						<xr:Item xsi:type="xr:MDObjectRef">Document.ОткрытиеСчетаДепо.Attribute.СчетДепо</xr:Item>
						<xr:Item xsi:type="xr:MDObjectRef">Document.ОтменаПредставителяСчетаДепо.Attribute.СчетДепо</xr:Item>
						<xr:Item xsi:type="xr:MDObjectRef">Document.ОперацииЦБ.Attribute.СчетДепо</xr:Item>
						<xr:Item xsi:type="xr:MDObjectRef">Document.ОткрытиеРазделаСчетаДепо.Attribute.СчетДепо</xr:Item>
						<xr:Item xsi:type="xr:MDObjectRef">Document.НазначениеПредставителяСчетаДепо.Attribute.СчетДепо</xr:Item>
						<xr:Item xsi:type="xr:MDObjectRef">Document.ЗакрытиеСчетаДепо.Attribute.СчетДепо</xr:Item>
					</References>
				</Properties>
			</Column>
			<Column uuid="5aea9375-c606-435b-826a-802d5ec8ea54">
				<Properties>
					<Name>Исполнитель</Name>
					<Synonym>
						<v8:item>
							<v8:lang>ru</v8:lang>
							<v8:content>Исполнитель</v8:content>
						</v8:item>
					</Synonym>
					<Comment/>
					<Indexing>Index</Indexing>
					<References>
						<xr:Item xsi:type="xr:MDObjectRef">Document.ОткрытиеСчетаДепо.Attribute.Автор</xr:Item>
						<xr:Item xsi:type="xr:MDObjectRef">Document.ОтменаПредставителяСчетаДепо.Attribute.Автор</xr:Item>
						<xr:Item xsi:type="xr:MDObjectRef">Document.ОперацииЦБ.Attribute.Автор</xr:Item>
						<xr:Item xsi:type="xr:MDObjectRef">Document.ОткрытиеРазделаСчетаДепо.Attribute.Автор</xr:Item>
						<xr:Item xsi:type="xr:MDObjectRef">Document.НазначениеПредставителяСчетаДепо.Attribute.Автор</xr:Item>
						<xr:Item xsi:type="xr:MDObjectRef">Document.ЗакрытиеСчетаДепо.Attribute.Автор</xr:Item>
					</References>
				</Properties>
			</Column>
			<Form>ФормаСписка</Form>
		</ChildObjects>
	</DocumentJournal>
</MetaDataObject>